odoo8_addon_report_qweb_element_page_visibility-8.0.1.0.0-py2.7-nspkg.pth
odoo_addons/report_qweb_element_page_visibility/__openerp__.py
odoo_addons/report_qweb_element_page_visibility/__init__.py
odoo_addons/report_qweb_element_page_visibility/README.rst
odoo_addons/report_qweb_element_page_visibility/views/layouts.xml
odoo_addons/report_qweb_element_page_visibility/static/description/icon.png
odoo8_addon_report_qweb_element_page_visibility-8.0.1.0.0.dist-info/top_level.txt
odoo8_addon_report_qweb_element_page_visibility-8.0.1.0.0.dist-info/WHEEL
odoo8_addon_report_qweb_element_page_visibility-8.0.1.0.0.dist-info/RECORD
odoo8_addon_report_qweb_element_page_visibility-8.0.1.0.0.dist-info/metadata.json
odoo8_addon_report_qweb_element_page_visibility-8.0.1.0.0.dist-info/DESCRIPTION.rst
odoo8_addon_report_qweb_element_page_visibility-8.0.1.0.0.dist-info/METADATA
odoo8_addon_report_qweb_element_page_visibility-8.0.1.0.0.dist-info/namespace_packages.txt
